ig_package/__init__.py
ig_package/main.py
ig_package-1.2.1.dist-info/LICENSE
ig_package-1.2.1.dist-info/METADATA
ig_package-1.2.1.dist-info/WHEEL
ig_package-1.2.1.dist-info/RECORD
