Metadata-Version: 2.1
Name: ig-package
Version: 1.2.1
Summary: A package allowing easy interaction with IG Group's REST API.
License: MIT
Author: hnewey7
Author-email: hnewey7@gmail.com
Requires-Python: >=3.11,<4.0
Classifier: License :: OSI Approved :: MIT License
Classifier: Programming Language :: Python :: 3
Classifier: Programming Language :: Python :: 3.11
Classifier: Programming Language :: Python :: 3.12
Requires-Dist: pandas (>=2.2.1,<3.0.0)
Requires-Dist: requests (>=2.31.0,<3.0.0)
Requires-Dist: trading-ig (>=0.0.22,<0.0.23)
